multiplex.py
multiplex_sh-1.0.0.data/data/share/doc/multiplex/LICENSE
multiplex_sh-1.0.0.data/data/share/doc/multiplex/README.md
multiplex_sh-1.0.0.data/data/share/multiplex/examples/README.md
multiplex_sh-1.0.0.data/data/share/multiplex/examples/actions-demo.sh
multiplex_sh-1.0.0.data/data/share/multiplex/examples/cicd-pipeline.sh
multiplex_sh-1.0.0.data/data/share/multiplex/examples/complete-demo.sh
multiplex_sh-1.0.0.data/data/share/multiplex/examples/dev-environment.sh
multiplex_sh-1.0.0.data/data/share/multiplex/examples/http-benchmark.sh
multiplex_sh-1.0.0.data/data/share/multiplex/examples/parallel-coordination.sh
multiplex_sh-1.0.0.data/data/share/multiplex/examples/process-delays.sh
multiplex_sh-1.0.0.data/data/share/multiplex/examples/sequential-build.sh
multiplex_sh-1.0.0.data/data/share/multiplex/examples/special-cases.sh
multiplex_sh-1.0.0.data/data/share/multiplex/examples/time-delays.sh
multiplex_sh-1.0.0.dist-info/LICENSE
multiplex_sh-1.0.0.dist-info/METADATA
multiplex_sh-1.0.0.dist-info/WHEEL
multiplex_sh-1.0.0.dist-info/entry_points.txt
multiplex_sh-1.0.0.dist-info/top_level.txt
multiplex_sh-1.0.0.dist-info/RECORD
