Metadata-Version: 2.1
Name: multiplex-sh
Version: 1.0.0
Summary: A command-line multiplexer for running multiple processes in parallel with coordination
Home-page: https://github.com/sebastien/multiplex
Author: Sébastien Pierre
Author-email: sebastien@ffctn.com
License: BSD-3-Clause
Project-URL: Bug Reports, https://github.com/sebastien/multiplex/issues
Project-URL: Source, https://github.com/sebastien/multiplex
Project-URL: Documentation, https://github.com/sebastien/multiplex#readme
Keywords: multiplex process command parallel concurrent shell cli automation build coordination orchestration
Platform: unix
Platform: linux
Platform: osx
Classifier: Development Status :: 5 - Production/Stable
Classifier: Environment :: Console
Classifier: Intended Audience :: Developers
Classifier: Intended Audience :: System Administrators
Classifier: License :: OSI Approved :: BSD License
Classifier: Operating System :: MacOS
Classifier: Operating System :: POSIX
Classifier: Operating System :: Unix
Classifier: Programming Language :: Python :: 3
Classifier: Programming Language :: Python :: 3.8
Classifier: Programming Language :: Python :: 3.9
Classifier: Programming Language :: Python :: 3.10
Classifier: Programming Language :: Python :: 3.11
Classifier: Programming Language :: Python :: 3.12
Classifier: Programming Language :: Python :: 3.13
Classifier: Programming Language :: Python :: 3 :: Only
Classifier: Topic :: Software Development :: Build Tools
Classifier: Topic :: System :: Systems Administration
Classifier: Topic :: Utilities
Classifier: Topic :: System :: Shells
Classifier: Topic :: System :: System Shells
Classifier: Topic :: Software Development :: Testing
Requires-Python: >=3.12
License-File: LICENSE
Provides-Extra: dev
Requires-Dist: pytest>=6.0; extra == "dev"
Requires-Dist: black>=22.0; extra == "dev"
Requires-Dist: flake8>=4.0; extra == "dev"
Requires-Dist: mypy>=0.950; extra == "dev"
Provides-Extra: test
Requires-Dist: pytest>=6.0; extra == "test"
Requires-Dist: pytest-cov>=2.0; extra == "test"
